spikify/__init__.py
spikify/encoding/__init__.py
spikify/encoding/rate/__init__.py
spikify/encoding/rate/poisson_rate_algorithm.py
spikify/encoding/temporal/__init__.py
spikify/encoding/temporal/contrast/__init__.py
spikify/encoding/temporal/contrast/moving_window_algorithm.py
spikify/encoding/temporal/contrast/step_forward_algorithm.py
spikify/encoding/temporal/contrast/threshold_based_algorithm.py
spikify/encoding/temporal/contrast/zero_cross_step_forward_algorithm.py
spikify/encoding/temporal/deconvolution/__init__.py
spikify/encoding/temporal/deconvolution/bens_spiker_algorithm.py
spikify/encoding/temporal/deconvolution/hough_spiker_algorithm.py
spikify/encoding/temporal/deconvolution/modified_hough_spiker_algorithm.py
spikify/encoding/temporal/deconvolution/utils.py
spikify/encoding/temporal/global_referenced/__init__.py
spikify/encoding/temporal/global_referenced/phase_encoding_algorithm.py
spikify/encoding/temporal/global_referenced/time_to_spike_algorithm.py
spikify/encoding/temporal/latency/__init__.py
spikify/encoding/temporal/latency/burst_encoding_algorithm.py
spikify/filtering/__init__.py
spikify/filtering/filterbank.py
spikify/version.py
innuce_spikify-0.3.0.dist-info/METADATA
innuce_spikify-0.3.0.dist-info/WHEEL
innuce_spikify-0.3.0.dist-info/licenses/AUTHORS
innuce_spikify-0.3.0.dist-info/licenses/LICENSE
innuce_spikify-0.3.0.dist-info/RECORD
