Metadata-Version: 2.4
Name: innuce-spikify
Version: 0.3.0
Summary: A Python package to convert signal data to spike trains
License: Apache-2.0
License-File: AUTHORS
License-File: LICENSE
Keywords: artificial intelligence,neuromorphic computing,signal processing,education
Author: Benedetto Leto
Author-email: benedetto.leto@polito.it
Requires-Python: >=3.10,<4.0
Classifier: Development Status :: 5 - Production/Stable
Classifier: Intended Audience :: Developers
Classifier: Intended Audience :: Education
Classifier: Intended Audience :: Science/Research
Classifier: License :: OSI Approved :: Apache Software License
Classifier: Operating System :: OS Independent
Classifier: Programming Language :: Python :: 3
Classifier: Programming Language :: Python :: 3.10
Classifier: Programming Language :: Python :: 3.11
Classifier: Programming Language :: Python :: 3.12
Classifier: Programming Language :: Python :: 3.13
Classifier: Programming Language :: Python :: 3.14
Classifier: Topic :: Scientific/Engineering
Classifier: Topic :: Scientific/Engineering :: Artificial Intelligence
Classifier: Topic :: Scientific/Engineering :: Electronic Design Automation (EDA)
Classifier: Topic :: Software Development :: Libraries :: Python Modules
Provides-Extra: code-quality
Provides-Extra: dev
Provides-Extra: docs
Provides-Extra: release
Requires-Dist: numpy (>=2.1.0)
Requires-Dist: scipy (>=1.14.1)
Project-URL: Documentation, https://spikify.readthedocs.io/en/latest/
Project-URL: Repository, https://github.com/neuromorphic-polito/spikify
